smaksimovich/__init__.py
smaksimovich/torch_utils.py
smaksimovich/utils.py
smaksimovich-1.0.1.dist-info/LICENSE
smaksimovich-1.0.1.dist-info/METADATA
smaksimovich-1.0.1.dist-info/WHEEL
smaksimovich-1.0.1.dist-info/top_level.txt
smaksimovich-1.0.1.dist-info/RECORD
